CONTRIBUTING.rst
HISTORY.rst
LICENSE
MANIFEST.in
README.rst
setup.cfg
setup.py
ultra_config_kms_cli.py
docs/Makefile
docs/conf.py
docs/contributing.rst
docs/history.rst
docs/index.rst
docs/installation.rst
docs/make.bat
docs/readme.rst
docs/usage.rst
ultra_config_kms_cli.egg-info/PKG-INFO
ultra_config_kms_cli.egg-info/SOURCES.txt
ultra_config_kms_cli.egg-info/dependency_links.txt
ultra_config_kms_cli.egg-info/entry_points.txt
ultra_config_kms_cli.egg-info/not-zip-safe
ultra_config_kms_cli.egg-info/requires.txt
ultra_config_kms_cli.egg-info/top_level.txt