Metadata-Version: 1.1
Name: ultra-config-kms-cli
Version: 0.1.0
Summary: A simple cli package for easily updating ECS task definition files with secrets
Home-page: https://github.com/Apptimize-OSS/ultra-config-kms-cli
Author: Apptimize (Tim Martin)
Author-email: engineering@apptimize.com
License: MIT license
Keywords: ultra_config_kms_cli
Platform: UNKNOWN
Classifier: Development Status :: 2 - Pre-Alpha
Classifier: Intended Audience :: Developers
Classifier: License :: OSI Approved :: MIT License
Classifier: Natural Language :: English
Classifier: Programming Language :: Python :: 2
Classifier: Programming Language :: Python :: 2.6
Classifier: Programming Language :: Python :: 2.7
Classifier: Programming Language :: Python :: 3
Classifier: Programming Language :: Python :: 3.3
Classifier: Programming Language :: Python :: 3.4
Classifier: Programming Language :: Python :: 3.5
